[
    {"type": "tf", "q": "Centripetal force is the force acting towards the centre of the circular path.", "c": true},
    {"type": "tf", "q": "Centrifugal force is a real force acting on an object along the string.", "c": false},
    {"type": "tf", "q": "Centrifugal force is an apparent or fictitious force equal and opposite to the centripetal force.", "c": true},
    {"type": "tf", "q": "The centrifugal force is caused by the effect of inertia.", "c": true},
    {"type": "tf", "q": "In a laboratory centrifuge, denser particles rise to the top of the tube.", "c": false},
    {"type": "tf", "q": "The sedimentation principle states that radial acceleration causes denser particles to settle to the bottom.", "c": true},
    {"type": "tf", "q": "A centrifugal pump converts mechanical energy into hydraulic energy.", "c": true},
    {"type": "tf", "q": "Hydraulic energy is also known as pressure energy.", "c": true},
    {"type": "tf", "q": "The centrifugal action of a washing machine is used to wash the clothes with soap.", "c": false},
    {"type": "tf", "q": "Centrifugal governors consist of two balls of equal mass attached to arms.", "c": true},
    {"type": "tf", "q": "The centrifugal governor is used to measure and regulate the speed of a machine.", "c": true},
    {"type": "tf", "q": "A satellite orbiting a planet is supported by the centrifugal force.", "c": false},
    {"type": "tf", "q": "Removing excess water by spin drying clothes is done with the help of centrifugal force.", "c": true},
    {"type": "tf", "q": "Centrifugal force results from the effect of inertia.", "c": true},
    {"type": "tf", "q": "Centripetal force is directed towards the axis of rotation or centre of curvature.", "c": true}
  ]
