[
    {"type":"mcq","q":"According to Newton's second law, an object that is accelerating must have:","a":["a constant velocity","a net force acting on it","no net force acting on it"],"c":1},
    {"type":"mcq","q":"For uniform circular motion, what is the status of the speed $v$?","a":["$v = \\text{variable}$","$v = 0$","$v = \\text{constant}$"],"c":2},
    {"type":"mcq","q":"In uniform circular motion, the acceleration is directed:","a":["towards the centre of the circle","away from the centre of the circle","tangent to the circle"],"c":0},
    {"type":"mcq","q":"What is the net force called that is directed towards the centre of the circle?","a":["centrifugal force","centripetal force","frictional force"],"c":1},
    {"type":"mcq","q":"In the absence of a centripetal force, an object would move in a:","a":["circle","curved path","straight line"],"c":2},
    {"type":"mcq","q":"Which law states that in the absence of a force, an object would move in a straight line?","a":["Newton's first law","Newton's second law","Newton's third law"],"c":0},
    {"type":"mcq","q":"The magnitude of the centripetal force is given by $F_c = m a_c = ...$","a":["$\\frac{m v}{r}$","$\\frac{m v^2}{r}$","$\\frac{m^2 v}{r}$"],"c":1},
    {"type":"mcq","q":"Substituting $v = r \\omega$ into the centripetal force equation results in $F_c = ...$","a":["$m r \\omega$","$m r^2 \\omega$","$m r \\omega^2$"],"c":2},
    {"type":"mcq","q":"Which of the following is an example of centripetal force?","a":["The gravitational force of the earth on the moon","The upward thrust of air on a stationary ball","The internal pressure of a gas container"],"c":0},
    {"type":"mcq","q":"The electric force acting on an electron orbiting the nucleus is an example of:","a":["centrifugal force","centripetal force","gravitational force"],"c":1},
    {"type":"mcq","q":"When whirling a body attached to a string, what kind of force is originated?","a":["frictional force","normal force","tension force"],"c":2},
    {"type":"mcq","q":"If the tension force is normal to the direction of motion at constant speed, it behaves as:","a":["a centrifugal force","a centripetal force","a gravitational force"],"c":1},
    {"type":"mcq","q":"An attractive force exists between the sun and the earth in a direction:","a":["parallel to the path of the earth","perpendicular to the path of the earth","opposite to the path of the earth"],"c":1},
    {"type":"mcq","q":"The attractive force between the nucleus and the electron is known as the:","a":["Coulomb attractive force","Newtonian attractive force","Einsteinian attractive force"],"c":0},
    {"type":"mcq","q":"When a car turns in a circular path, what force exists between the road and the car tires?","a":["tension force","frictional force","upward thrust"],"c":1},
    {"type":"mcq","q":"The frictional force on a car turning in a circle acts:","a":["tangentially to the motion","normally to the direction of motion","opposite to the direction of motion"],"c":1},
    {"type":"mcq","q":"When a car moves in a circular path inclined to the horizontal, the road exerts:","a":["a tension force","a reaction force","a gravitational force"],"c":1},
    {"type":"mcq","q":"The reaction force of the road is also known as the:","a":["centripetal force","normal force","frictional force"],"c":1},
    {"type":"mcq","q":"The component of the normal force that acts towards the centre of the circle is the:","a":["horizontal component","vertical component","diagonal component"],"c":0},
    {"type":"mcq","q":"Which component of the normal force is the required centripetal force on an inclined path?","a":["vertical component","horizontal component","frictional component"],"c":1},
    {"type":"mcq","q":"The upward thrust on an aeroplane body is also called:","a":["centrifugal force","lifting force","gravitational force"],"c":1},
    {"type":"mcq","q":"When an aeroplane tilts, which component of the lifting force provides the centripetal force?","a":["vertical component","horizontal component","normal component"],"c":1},
    {"type":"mcq","q":"On a flat (unbanked) road, centripetal force is supplied by:","a":["the normal force","friction between tires and road","the weight of the car"],"c":1},
    {"type":"mcq","q":"In the equation $F_f = \\frac{mv^2}{r}$, what does $r$ represent?","a":["radius of the path","rotation speed","reaction force"],"c":0},
    {"type":"mcq","q":"Under wet and slippery conditions, what may happen if frictional force is not sufficient?","a":["The car will stop immediately","The car will skid out of the circular path","The car will move faster"],"c":1},
    {"type":"mcq","q":"What is the practice of raising the outer edge of a curved road higher than the inner edge called?","a":["Frictioning of roads","Banking of roads","Leveling of roads"],"c":1},
    {"type":"mcq","q":"The angle that the inclined track makes with the horizontal is called the:","a":["angle of friction","angle of inclination","angle of banking"],"c":2},
    {"type":"mcq","q":"The normal force $F_N$ exerted by a banked road is:","a":["parallel to the road","perpendicular to the road","horizontal to the road"],"c":1},
    {"type":"mcq","q":"For every banked curve, there is a speed at which no frictional force is required called:","a":["maximum speed","limiting speed","minimum speed"],"c":1},
    {"type":"mcq","q":"The horizontal component of the normal force, $F_N \\sin \\theta$, is equal to:","a":["$mg$","$\\frac{mv^2}{r}$","$mr\\omega$"],"c":1},
    {"type":"mcq","q":"If there is no vertical motion for a car on a banked road, the net force in the y direction is:","a":["zero","positive","negative"],"c":0},
    {"type":"mcq","q":"The vertical component of the normal force is $F_N \\cos \\theta = ...$","a":["$ma$","$\\frac{mv^2}{r}$","$mg$"],"c":2},
    {"type":"mcq","q":"Which equation represents the banking angle $\\theta$?","a":["$\\tan \\theta = \\frac{v^2}{rg}$","$\\sin \\theta = \\frac{v}{rg}$","$\\cos \\theta = \\frac{v^2}{r}$"],"c":0},
    {"type":"mcq","q":"The banking angle of a road $\\theta$ is chosen so that the condition holds for:","a":["static friction","limiting speed $v$","maximum mass $m$"],"c":1},
    {"type":"mcq","q":"The centripetal acceleration is directed towards the ___ of the circle at any moment.","a":["circumference","centre","tangent"],"c":1},
    {"type":"mcq","q":"A force is needed to deviate an object from its ___ path to move in a circle.","c":2,"a":["circular","curved","straight line"]},
    {"type":"mcq","q":"The gravitational force of the sun on the planets provides:","a":["centrifugal force","centripetal force","normal force"],"c":1},
    {"type":"mcq","q":"When a car makes a turn on an unbanked road, the frictional force $F_f$ acts upon the:","a":["steering wheel","brakes","tires of the car"],"c":2},
    {"type":"mcq","q":"To prevent skidding on curves, roads must be:","a":["paved with rubber","banked","made perfectly flat"],"c":1},
    {"type":"mcq","q":"$F_N \\sin \\theta$ acts towards the:","a":["top of the incline","centre of the curve","bottom of the incline"],"c":1},
    {"type":"mcq","q":"The net force on the car in the y direction is zero because there is no:","a":["horizontal motion","circular motion","vertical motion"],"c":2},
    {"type":"mcq","q":"In the banking angle formula $\\tan \\theta = \\frac{v^2}{rg}$, what does $g$ represent?","a":["gradient of the road","acceleration due to gravity","gear ratio"],"c":1},
    {"type":"mcq","q":"The required centripetal force for an electron is provided by:","a":["gravitational force","Coulomb attractive force","tension force"],"c":1},
    {"type":"mcq","q":"A ball on the end of a string whirled in a circle experiences a force called:","a":["centrifugal force","centripetal force","buoyant force"],"c":1},
    {"type":"mcq","q":"The horizontal component of normal force $F_N \\sin \\theta$ equals the centripetal force:","a":["$\\frac{mv}{r}$","$\\frac{mv^2}{r}$","$mrg$"],"c":1},
    {"type":"mcq","q":"The reaction force of the road acts ___ to the car.","a":["parallel","tangentially","normally"],"c":2},
    {"type":"mcq","q":"The tension in a string provides the centripetal force for a ball to:","a":["stop moving","keep moving in circular path","move in a straight line"],"c":1},
    {"type":"mcq","q":"If a car moves in a circular path inclined to the horizontal, the normal force is resolved into:","a":["two components","three components","four components"],"c":0},
    {"type":"mcq","q":"Centripetal force is the ___ force directed towards the centre.","a":["total","net","average"],"c":1},
    {"type":"mcq","q":"The magnitude of centripetal force is $F_c = ...$","a":["$m a_c$","$m v^2$","$m r \\omega$"],"c":0}
  ]
