[
    {"type": "tf", "q": "Optics is the branch of physics that studies the nature and properties of light.", "c": true},
    {"type": "tf", "q": "LASER is an acronym for Light Amplification by Stimulated Emission of Radiation.", "c": true},
    {"type": "tf", "q": "A laser is a source of a narrow beam of intense, monochromatic, coherent light.", "c": true},
    {"type": "tf", "q": "Lasers can only produce light in the visible part of the electromagnetic radiation.", "c": false},
    {"type": "tf", "q": "A continuous laser beam can range in power from a fraction of a milliwatt to more than a megawatt.", "c": true},
    {"type": "tf", "q": "Lasers are classified into five main types, including fiber lasers and dye lasers.", "c": true},
    {"type": "tf", "q": "A laser contains three essential elements: laser medium, power supply, and optical cavity.", "c": true},
    {"type": "tf", "q": "The process of supplying energy to the laser medium to excite it to emit light is called pumping.", "c": true},
    {"type": "tf", "q": "The optical cavity concentrates light to stimulate the emission of laser radiation.", "c": true},
    {"type": "tf", "q": "The optical cavity consists of two highly reflective mirrors, one of which allows some light to come out as a laser beam.", "c": true},
    {"type": "tf", "q": "Two essential processes to initiate a laser action are stimulated emission and population inversion.", "c": true},
    {"type": "tf", "q": "In population inversion, the population of the upper level of a transition is lower than that of the lower level.", "c": false},
    {"type": "tf", "q": "Coherence means that the light waves a laser contains are in phase with one another.", "c": true},
    {"type": "tf", "q": "Lasers are used in bloodless surgery and destroying kidney stones.", "c": true},
    {"type": "tf", "q": "Laser light is used to collect information from the bar code printed on products.", "c": true}
  ]
